odoo/addons/sale_coupon_order_pending/README.rst
odoo/addons/sale_coupon_order_pending/__init__.py
odoo/addons/sale_coupon_order_pending/__manifest__.py
odoo/addons/sale_coupon_order_pending/i18n/sale_coupon_order_pending.pot
odoo/addons/sale_coupon_order_pending/models/__init__.py
odoo/addons/sale_coupon_order_pending/models/coupon_coupon.py
odoo/addons/sale_coupon_order_pending/models/sale_order.py
odoo/addons/sale_coupon_order_pending/readme/CONTRIBUTORS.rst
odoo/addons/sale_coupon_order_pending/readme/DESCRIPTION.rst
odoo/addons/sale_coupon_order_pending/readme/USAGE.rst
odoo/addons/sale_coupon_order_pending/static/description/icon.png
odoo/addons/sale_coupon_order_pending/static/description/index.html
odoo/addons/sale_coupon_order_pending/tests/__init__.py
odoo/addons/sale_coupon_order_pending/tests/test_sale_coupon_order_pending.py
odoo/addons/sale_coupon_order_pending/views/coupon_coupon_views.xml
odoo/addons/sale_coupon_order_pending/views/sale_order_views.xml
odoo13_addon_sale_coupon_order_pending-13.0.1.0.1.dev2.dist-info/METADATA
odoo13_addon_sale_coupon_order_pending-13.0.1.0.1.dev2.dist-info/WHEEL
odoo13_addon_sale_coupon_order_pending-13.0.1.0.1.dev2.dist-info/top_level.txt
odoo13_addon_sale_coupon_order_pending-13.0.1.0.1.dev2.dist-info/RECORD
